smb/__init__.py
smb/smb.py
smb/utils.py
smb_optimizer-0.1.1.dist-info/WHEEL
smb_optimizer-0.1.1.dist-info/METADATA
smb_optimizer-0.1.1.dist-info/RECORD
